{"feed_type":"RSS2","id":"86d2072d7a8329cdf16ebcc1f2595ded","title":{"content_type":"text/plain","src":null,"content":"Il Giornale - Cronache"},"updated":null,"authors":[],"description":{"content_type":"text/plain","src":null,"content":"Ultime notizie"},"links":[{"href":"https://www.ilgiornale.it/taxonomy/term/40821/feed","rel":null,"media_type":null,"href_lang":null,"title":null,"length":null},{"href":"https://www.ilgiornale.it/taxonomy/term/40821/feed","rel":"self","media_type":null,"href_lang":null,"title":null,"length":null}],"categories":[],"contributors":[],"generator":null,"icon":null,"language":"it","logo":null,"published":null,"rating":null,"rights":{"content_type":"text/plain","src":null,"content":"Copyright (c) 2022 Il Giornale Online"},"ttl":null,"entries":[{"id":"https://www.ilgiornale.it/news/cronaca-nera/caso-saman-abbas-arrestato-pakistan-padre-shabbar-2085649.html","title":{"content_type":"text/plain","src":null,"content":"Arrestato in Pakistan Shabbar Abbas. In Italia è accusato per l'omicidio di Saman"},"updated":"2022-11-15T20:15:04Z","authors":[{"name":"author","uri":null,"email":"redazione@ilgiornale-web.it (Angela Leucci)"}],"content":null,"links":[{"href":"https://www.ilgiornale.it/news/cronaca-nera/caso-saman-abbas-arrestato-pakistan-padre-shabbar-2085649.html","rel":null,"media_type":null,"href_lang":null,"title":null,"length":null}],"summary":{"content_type":"text/html","src":null,"content":"<figure><img src=\"https://img.ilgcdn.com/sites/default/files/styles/md/public/foto/2022/09/30/1664568527-schermata-2022-09-30-214250.jpg?_=1664568527\" width=\"500\" height=\"280\" alt=\"\" /></figure>È stato arrestato in Pakistan per frode Shabbar, padre di Saman Abbas. In Italia l&#39;uomo è accusato di essere il mandante di un presunto delitto d&#39;onore"},"categories":[{"term":"Cronaca nera","scheme":null,"label":null,"subcategories":[]}],"contributors":[],"published":"2022-11-15T20:15:04Z","source":null,"rights":null,"media":[],"language":null,"base":null}]}