{"feed_type":"Atom","id":"example","title":null,"updated":null,"authors":[],"description":null,"links":[],"categories":[],"contributors":[],"generator":null,"icon":null,"language":null,"logo":null,"published":null,"rating":null,"rights":null,"ttl":null,"entries":[{"id":"75ffea6b731bb4534f3138fd6b726791","title":{"content_type":"text/plain","src":null,"content":"The Day Off: Tampa"},"updated":"2019-04-05T21:04:41Z","authors":[{"name":"Some author","uri":null,"email":null}],"content":{"body":"Some text","content_type":"text/html","length":null,"src":null},"links":[{"href":"http://www.example.com/the-day-off-tampa","rel":"alternate","media_type":null,"href_lang":null,"title":null,"length":null}],"summary":null,"categories":[],"contributors":[],"published":"2019-04-05T21:04:40Z","source":null,"rights":null,"media":[{"title":{"content_type":"text/plain","src":null,"content":"media title"},"content":[{"url":"https://www.example.com/Zz1hNjRiMWFjMzdhYWIzNTEwNjk2YjIzYjc5NWQxNWFlMA==/.jpeg","content_type":"image/jpeg","height":1365,"width":2048,"duration":null,"size":null,"rating":null}],"duration":null,"thumbnails":[{"image":{"uri":"https://www.example.com/Zz1hNjRiMWFjMzdhYWIzNTEwNjk2YjIzYjc5NWQxNWFlMA==?width=75&height=75","title":null,"link":null,"width":2048,"height":1365,"description":null},"time":null}],"texts":[{"text":{"content_type":"text/plain","src":null,"content":"media text"},"start_time":null,"end_time":null}],"description":{"content_type":"text/plain","src":null,"content":"media description"},"community":null,"credits":[{"entity":"media credit"}]}],"language":null,"base":null}]}